aprilgrid/__about__.py
aprilgrid/__init__.py
aprilgrid/common.py
aprilgrid/detection.py
aprilgrid/detector.py
aprilgrid/tag_codes.py
aprilgrid/tag_family.py
aprilgrid-0.5.0.dist-info/METADATA
aprilgrid-0.5.0.dist-info/WHEEL
aprilgrid-0.5.0.dist-info/licenses/LICENSE
aprilgrid-0.5.0.dist-info/RECORD
