Metadata-Version: 2.4
Name: aprilgrid
Version: 0.5.0
Summary: Pure python version of aprilgrid.
Project-URL: Source, https://github.com/powei-lin/aprilgrid
Project-URL: Documentation, https://github.com/powei-lin/aprilgrid#readme
Project-URL: Issues, https://github.com/powei-lin/aprilgrid/issues
Author-email: Powei Lin <poweilin1994@gmail.com>
License-Expression: BSD-3-Clause
License-File: LICENSE
Classifier: Development Status :: 4 - Beta
Classifier: Programming Language :: Python
Classifier: Programming Language :: Python :: 3.8
Classifier: Programming Language :: Python :: 3.9
Classifier: Programming Language :: Python :: 3.10
Classifier: Programming Language :: Python :: 3.11
Classifier: Programming Language :: Python :: 3.12
Classifier: Programming Language :: Python :: Implementation :: CPython
Classifier: Programming Language :: Python :: Implementation :: PyPy
Requires-Python: >=3.8
Requires-Dist: numpy
Requires-Dist: opencv-python
